[
    {
        "step_id":"",
        "cf_master_id":"",
        "category_id":"",
        "name": "Firma informasjon",
        "description": "Hvis selskapet finnes i Brønnlysundregistrene henter vi aktuell informasjon og forhåndsutfyller for deg.",
        "sort_order": 0,
        "step": 0,
        "block_data": [
            {
                "block_id":"",
                "client_id":"",
                "cf_master_id":"",
                "cf_step_id":"",
                "category_id":"",
                "title": "Firma informasjon",
                "description": "Hvis selskapet finnes i Brønnlysundregistrene henter vi aktuell informasjon og forhåndsutfyller for deg.",
                "sort_order": 1,
                "attributes": [
                    {
                        "attribute_id":"",
                        "client_id":"",
                        "cf_master_id":"",
                        "cf_step_id":"",
                        "cf_block_id":"",
                        "label": "Company Form",
                        "description": "",
                        "type": "companyform",
                        "is_mandetory": "0",
                        "attribute_options": "",
                        "default_value": "",
                        "is_conditional": 0,
                        "show_on_field": 0,
                        "show_on_value": "",
                        "default_task_notes": "",
                        "default_task_attachments": "",
                        "default_task_rule": "",
                        "sort_order": 1
                    }
                ]
            },
            {
                "block_id":"",
                "client_id":"",
                "cf_master_id":"",
                "cf_step_id":"",
                "category_id":"",
                "title": "Kontaktpersoner",
                "description": "Hvis selskapet finnes i Brønnlysundregistrene henter vi aktuell informasjon og forhåndsutfyller for deg.",
                "sort_order": 2,
                "attributes": [
                    {
                        "attribute_id":"",
                        "client_id":"",
                        "cf_master_id":"",
                        "cf_step_id":"",
                        "cf_block_id":"",
                        "label": "Contact Person Form",
                        "description": "",
                        "type": "contactpersonform",
                        "is_mandetory": "0",
                        "attribute_options": "",
                        "default_value": "",
                        "is_conditional": 0,
                        "show_on_field": 0,
                        "show_on_value": "",
                        "default_task_notes": "",
                        "default_task_attachments": "",
                        "default_task_rule": "",
                        "sort_order": 2
                    }
                ]
            },
            {
                "block_id":"",
                "client_id":"",
                "cf_master_id":"",
                "cf_step_id":"",
                "category_id":"",
                "title": "Kommentar",
                "description": "Hvis selskapet finnes i Brønnlysundregistrene henter vi aktuell informasjon og forhåndsutfyller for deg.",
                "sort_order": 3,
                "attributes": [
                    {
                        "attribute_id":"",
                        "client_id":"",
                        "cf_master_id":"",
                        "cf_step_id":"",
                        "cf_block_id":"",
                        "label": "Kommentar",
                        "description": "",
                        "type": "textarea",
                        "is_mandetory": "0",
                        "attribute_options": "",
                        "default_value": "",
                        "is_conditional": 0,
                        "show_on_field": 0,
                        "show_on_value": "",
                        "default_task_notes": "",
                        "default_task_attachments": "",
                        "default_task_rule": "",
                        "sort_order": 3
                    }
                ]
            }
        ]
    },
    {
        "step_id":"",
        "cf_master_id":"",
        "category_id":"",
        "name": "Om oppdraget",
        "description": "Hvis selskapet finnes i Brønnlysundregistrene henter vi aktuell informasjon og forhåndsutfyller for deg.",
        "sort_order": 1,
        "step": 1,
        "block_data": [
            {
                "block_id":"",
                "client_id":"",
                "cf_master_id":"",
                "cf_step_id":"",
                "category_id":"",
                "title": "Oppdragsansvarlig",
                "description": "Hvis selskapet finnes i Brønnlysundregistrene henter vi aktuell informasjon og forhåndsutfyller for deg.",
                "sort_order": 1,
                "attributes": [
                    {
                        "attribute_id":"",
                        "client_id":"",
                        "cf_master_id":"",
                        "cf_step_id":"",
                        "cf_block_id":"",
                        "label": "Hvem er ansvarlig?",
                        "description": "",
                        "type": "assignaccountantdropdown",
                        "is_mandetory": "0",
                        "attribute_options": "",
                        "default_value": "",
                        "is_conditional": 0,
                        "show_on_field": 0,
                        "show_on_value": "",
                        "default_task_notes": "",
                        "default_task_attachments": "",
                        "default_task_rule": "",
                        "sort_order": 1
                    }
                ]
            },
            {
                "block_id":"",
                "client_id":"",
                "cf_master_id":"",
                "cf_step_id":"",
                "category_id":"",
                "title": "Andre som skal ha tilgang",
                "description": "Hvis selskapet finnes i Brønnlysundregistrene henter vi aktuell informasjon og forhåndsutfyller for deg.",
                "sort_order": 2,
                "attributes": [
                    {
                        "attribute_id":"",
                        "client_id":"",
                        "cf_master_id":"",
                        "cf_step_id":"",
                        "cf_block_id":"",
                        "label": "Hvem er ansvarlig?",
                        "description": "",
                        "type": "assignaccountantform",
                        "is_mandetory": "0",
                        "attribute_options": "",
                        "default_value": "",
                        "is_conditional": 0,
                        "show_on_field": 0,
                        "show_on_value": "",
                        "default_task_notes": "",
                        "default_task_attachments": "",
                        "default_task_rule": "",
                        "sort_order": 1
                    }
                ]
            },
            {
                "block_id":"",
                "client_id":"",
                "cf_master_id":"",
                "cf_step_id":"",
                "category_id":"",
                "title": "Oppstartsdato",
                "description": "Hvis selskapet finnes i Brønnlysundregistrene henter vi aktuell informasjon og forhåndsutfyller for deg.",
                "sort_order": 3,
                "attributes": [
                    {
                        "attribute_id":"",
                        "client_id":"",
                        "cf_master_id":"",
                        "cf_step_id":"",
                        "cf_block_id":"",
                        "label": "Oppdragsavtalen gjelder fra",
                        "description": "",
                        "type": "date",
                        "is_mandetory": "0",
                        "attribute_options": "",
                        "default_value": "",
                        "is_conditional": 0,
                        "show_on_field": 0,
                        "show_on_value": "",
                        "default_task_notes": "",
                        "default_task_attachments": "",
                        "default_task_rule": "",
                        "sort_order": 1
                    },
                    {
                        "attribute_id":"",
                        "client_id":"",
                        "cf_master_id":"",
                        "cf_step_id":"",
                        "cf_block_id":"",
                        "label": "Kommentar",
                        "description": "",
                        "type": "textarea",
                        "is_mandetory": "0",
                        "attribute_options": "",
                        "default_value": "",
                        "is_conditional": 0,
                        "show_on_field": 0,
                        "show_on_value": "",
                        "default_task_notes": "",
                        "default_task_attachments": "",
                        "default_task_rule": "",
                        "sort_order": 2
                    }
                ]
            },
            {
                "block_id":"",
                "client_id":"",
                "cf_master_id":"",
                "cf_step_id":"",
                "category_id":"",
                "title": "Om oppdraget",
                "description": "Hvis selskapet finnes i Brønnlysundregistrene henter vi aktuell informasjon og forhåndsutfyller for deg.",
                "sort_order": 4,
                "attributes": [
                    {
                        "attribute_id":"",
                        "client_id":"",
                        "cf_master_id":"",
                        "cf_step_id":"",
                        "cf_block_id":"",
                        "label": "Oppsigelsestid",
                        "description": "",
                        "type": "selectbox",
                        "is_mandetory": "0",
                        "attribute_options": "1|2|3",
                        "default_value": "",
                        "is_conditional": 0,
                        "show_on_field": 0,
                        "show_on_value": "",
                        "default_task_notes": "",
                        "default_task_attachments": "",
                        "default_task_rule": "",
                        "sort_order": 1
                    },
                    {
                        "attribute_id":"",
                        "client_id":"",
                        "cf_master_id":"",
                        "cf_step_id":"",
                        "cf_block_id":"",
                        "label": "Kommentar",
                        "description": "",
                        "type": "textarea",
                        "is_mandetory": "0",
                        "attribute_options": "",
                        "default_value": "",
                        "is_conditional": 0,
                        "show_on_field": 0,
                        "show_on_value": "",
                        "default_task_notes": "",
                        "default_task_attachments": "",
                        "default_task_rule": "",
                        "sort_order": 2
                    }
                ]
            }
        ]
    },
    {
        "step": 2,
        "step_id":"",
        "cf_master_id":"",
        "category_id":"",
        "name": "",
        "description": "",
        "sort_order": 2,
        "block_data": [
            {
                "block_id":"",
                "client_id":"",
                "cf_master_id":"",
                "cf_step_id":"",
                "category_id":"",
                "title": "Bokføring",
                "description": "Hvis selskapet finnes i Brønnlysundregistrene henter vi aktuell informasjon og forhåndsutfyller for deg.",
                "sort_order": 1,
                "attributes": [
                    {
                        "attribute_id":"",
                        "client_id":"",
                        "cf_master_id":"",
                        "cf_step_id":"",
                        "cf_block_id":"",
                        "label": "Hvem skal bokføre?",
                        "description": "",
                        "type": "selectbox",
                        "is_mandetory": "0",
                        "attribute_options": "Kunden selv|Regnskapsbyrå",
                        "default_value": "",
                        "is_conditional": 0,
                        "show_on_field": 0,
                        "show_on_value": "",
                        "default_task_notes": "",
                        "default_task_attachments": "",
                        "default_task_rule": "",
                        "sort_order": 1
                    },
                    {
                        "attribute_id":"",
                        "client_id":"",
                        "cf_master_id":"",
                        "cf_step_id":"",
                        "cf_block_id":"",
                        "label": "Kommentar",
                        "description": "",
                        "type": "textarea",
                        "is_mandetory": "0",
                        "attribute_options": "",
                        "default_value": "",
                        "is_conditional": 0,
                        "show_on_field": 0,
                        "show_on_value": "",
                        "default_task_notes": "",
                        "default_task_attachments": "",
                        "default_task_rule": "",
                        "sort_order": 2
                    }
                ]
            },
            {
                "block_id":"",
                "client_id":"",
                "cf_master_id":"",
                "cf_step_id":"",
                "category_id":"",
                "title": "Regnskap",
                "description": "Hvis selskapet finnes i Brønnlysundregistrene henter vi aktuell informasjon og forhåndsutfyller for deg.",
                "sort_order": 2,
                "attributes": [
                    {
                        "attribute_id":"",
                        "client_id":"",
                        "cf_master_id":"",
                        "cf_step_id":"",
                        "cf_block_id":"",
                        "label": "Hvordan overleveres bilag?",
                        "description": "",
                        "type": "selectbox",
                        "is_mandetory": "0",
                        "attribute_options": "1|2|3",
                        "default_value": "",
                        "is_conditional": 0,
                        "show_on_field": 0,
                        "show_on_value": "",
                        "default_task_notes": "",
                        "default_task_attachments": "",
                        "default_task_rule": "",
                        "sort_order": 1
                    },
                    {
                        "attribute_id":"",
                        "client_id":"",
                        "cf_master_id":"",
                        "cf_step_id":"",
                        "cf_block_id":"",
                        "label": "Kommentar",
                        "description": "",
                        "type": "textarea",
                        "is_mandetory": "0",
                        "attribute_options": "",
                        "default_value": "",
                        "is_conditional": 0,
                        "show_on_field": 0,
                        "show_on_value": "",
                        "default_task_notes": "",
                        "default_task_attachments": "",
                        "default_task_rule": "",
                        "sort_order": 2
                    },
                    {
                        "attribute_id":"",
                        "client_id":"",
                        "cf_master_id":"",
                        "cf_step_id":"",
                        "cf_block_id":"",
                        "label": "Oppgaver",
                        "description": "Hvis selskapet finnes i Brønnlysundregistrene henter vi aktuell informasjon og forhåndsutfyller for deg.",
                        "type": "freetext",
                        "is_mandetory": "0",
                        "attribute_options": "",
                        "default_value": "",
                        "is_conditional": 0,
                        "show_on_field": 0,
                        "show_on_value": "",
                        "default_task_notes": "",
                        "default_task_attachments": "",
                        "default_task_rule": "",
                        "sort_order": 3
                    },
                    {
                        "attribute_id":"",
                        "client_id":"",
                        "cf_master_id":"",
                        "cf_step_id":"",
                        "cf_block_id":"",
                        "label": "Minne kunden på å levere bilag",
                        "description": "",
                        "type": "taskform",
                        "is_mandetory": "0",
                        "attribute_options": "",
                        "default_value": "",
                        "is_conditional": 0,
                        "show_on_field": 0,
                        "show_on_value": "",
                        "default_task_notes": "",
                        "default_task_attachments": "",
                        "default_task_rule": "",
                        "sort_order": 4
                    },
                    {
                        "attribute_id":"",
                        "client_id":"",
                        "cf_master_id":"",
                        "cf_step_id":"",
                        "cf_block_id":"",
                        "label": "Føre bilag",
                        "description": "",
                        "type": "taskform",
                        "is_mandetory": "0",
                        "attribute_options": "",
                        "default_value": "",
                        "is_conditional": 0,
                        "show_on_field": 0,
                        "show_on_value": "",
                        "default_task_notes": "",
                        "default_task_attachments": "",
                        "default_task_rule": "",
                        "sort_order": 5
                    }
                ]
            }
        ]
    },
    {
        "step": 3,
        "step_id":"",
        "cf_master_id":"",
        "category_id":"",
        "name": "",
        "description": "",
        "sort_order": 3,
        "block_data": [
            {
                "block_id":"",
                "client_id":"",
                "cf_master_id":"",
                "cf_step_id":"",
                "category_id":"",
                "title": "Antall MVA-terminer",
                "description": "Hvis selskapet finnes i Brønnlysundregistrene henter vi aktuell informasjon og forhåndsutfyller for deg.",
                "sort_order": 1,
                "attributes": [
                    {
                        "attribute_id":"",
                        "client_id":"",
                        "cf_master_id":"",
                        "cf_step_id":"",
                        "cf_block_id":"",
                        "label": "Hvor mange terminer?",
                        "description": "",
                        "type": "selectbox",
                        "is_mandetory": "0",
                        "attribute_options": "1|6|12",
                        "default_value": "",
                        "is_conditional": 0,
                        "show_on_field": 0,
                        "show_on_value": "",
                        "default_task_notes": "",
                        "default_task_attachments": "",
                        "default_task_rule": "",
                        "sort_order": 1
                    },
                    {
                        "attribute_id":"",
                        "client_id":"",
                        "cf_master_id":"",
                        "cf_step_id":"",
                        "cf_block_id":"",
                        "label": "Kommentar",
                        "description": "",
                        "type": "textarea",
                        "is_mandetory": "0",
                        "attribute_options": "",
                        "default_value": "",
                        "is_conditional": 0,
                        "show_on_field": 0,
                        "show_on_value": "",
                        "default_task_notes": "",
                        "default_task_attachments": "",
                        "default_task_rule": "",
                        "sort_order": 2
                    },
                    {
                        "attribute_id":"",
                        "client_id":"",
                        "cf_master_id":"",
                        "cf_step_id":"",
                        "cf_block_id":"",
                        "label": "Oppgaver",
                        "description": "Hvis selskapet finnes i Brønnlysundregistrene henter vi aktuell informasjon og forhåndsutfyller for deg.",
                        "type": "freetext",
                        "is_mandetory": "0",
                        "attribute_options": "",
                        "default_value": "",
                        "is_conditional": 0,
                        "show_on_field": 0,
                        "show_on_value": "",
                        "default_task_notes": "",
                        "default_task_attachments": "",
                        "default_task_rule": "",
                        "sort_order": 3
                    },
                    {
                        "attribute_id":"",
                        "client_id":"",
                        "cf_master_id":"",
                        "cf_step_id":"",
                        "cf_block_id":"",
                        "label": "Levere MVA-melding",
                        "description": "",
                        "type": "taskform",
                        "is_mandetory": "0",
                        "attribute_options": "",
                        "default_value": "",
                        "is_conditional": 0,
                        "show_on_field": 0,
                        "show_on_value": "",
                        "default_task_notes": "",
                        "default_task_attachments": "",
                        "default_task_rule": "",
                        "sort_order": 4
                    }
                ]
            },
            {
                "block_id":"",
                "client_id":"",
                "cf_master_id":"",
                "cf_step_id":"",
                "category_id":"",
                "title": "Merverdikompensasjon",
                "description": "Hvis selskapet finnes i Brønnlysundregistrene henter vi aktuell informasjon og forhåndsutfyller for deg.",
                "sort_order": 2,
                "attributes": [
                    {
                        "attribute_id":"",
                        "client_id":"",
                        "cf_master_id":"",
                        "cf_step_id":"",
                        "cf_block_id":"",
                        "label": "Får kunden merverdikompensasjon?",
                        "description": "",
                        "type": "boolean",
                        "is_mandetory": "0",
                        "attribute_options": "Ja|Nei",
                        "default_value": "",
                        "is_conditional": 0,
                        "show_on_field": 0,
                        "show_on_value": "",
                        "default_task_notes": "",
                        "default_task_attachments": "",
                        "default_task_rule": "",
                        "sort_order": 1
                    },
                    {
                        "attribute_id":"",
                        "client_id":"",
                        "cf_master_id":"",
                        "cf_step_id":"",
                        "cf_block_id":"",
                        "label": "Kommentar",
                        "description": "",
                        "type": "textarea",
                        "is_mandetory": "0",
                        "attribute_options": "",
                        "default_value": "",
                        "is_conditional": 1,
                        "show_on_field": 0,
                        "show_on_value": "ja",
                        "default_task_notes": "",
                        "default_task_attachments": "",
                        "default_task_rule": "",
                        "sort_order": 2
                    },
                    {
                        "attribute_id":"",
                        "client_id":"",
                        "cf_master_id":"",
                        "cf_step_id":"",
                        "cf_block_id":"",
                        "label": "Oppgaver",
                        "description": "Hvis selskapet finnes i Brønnlysundregistrene henter vi aktuell informasjon og forhåndsutfyller for deg.",
                        "type": "freetext",
                        "is_mandetory": "0",
                        "attribute_options": "",
                        "default_value": "",
                        "is_conditional": 1,
                        "show_on_field": 0,
                        "show_on_value": "ja",
                        "default_task_notes": "",
                        "default_task_attachments": "",
                        "default_task_rule": "",
                        "sort_order": 3
                    },
                    {
                        "attribute_id":"",
                        "client_id":"",
                        "cf_master_id":"",
                        "cf_step_id":"",
                        "cf_block_id":"",
                        "label": "Forberede merverdikompensasjon",
                        "description": "",
                        "type": "taskform",
                        "is_mandetory": "0",
                        "attribute_options": "",
                        "default_value": "",
                        "is_conditional": 1,
                        "show_on_field": 0,
                        "show_on_value": "ja",
                        "default_task_notes": "",
                        "default_task_attachments": "",
                        "default_task_rule": "",
                        "sort_order": 4
                    },
                    {
                        "attribute_id":"",
                        "client_id":"",
                        "cf_master_id":"",
                        "cf_step_id":"",
                        "cf_block_id":"",
                        "label": "Levere mererdikompensasjon",
                        "description": "",
                        "type": "taskform",
                        "is_mandetory": "0",
                        "attribute_options": "",
                        "default_value": "",
                        "is_conditional": 1,
                        "show_on_field": 0,
                        "show_on_value": "ja",
                        "default_task_notes": "",
                        "default_task_attachments": "",
                        "default_task_rule": "",
                        "sort_order": 5
                    }
                ]
            }
        ]
    },
    {
        "step": 4,
        "step_id":"",
        "cf_master_id":"",
        "category_id":"",
        "sort_order": 4,
        "block_data": [
            {
                "block_id":"",
                "client_id":"",
                "cf_master_id":"",
                "cf_step_id":"",
                "category_id":"",
                "title": "Periodisk rapport",
                "description": "Hvis selskapet finnes i Brønnlysundregistrene henter vi aktuell informasjon og forhåndsutfyller for deg.",
                "sort_order": 3,
                "attributes": [
                    {
                        "attribute_id":"",
                        "client_id":"",
                        "cf_master_id":"",
                        "cf_step_id":"",
                        "cf_block_id":"",
                        "label": "Periodisk rapportering",
                        "description": "",
                        "type": "boolean",
                        "is_mandetory": "0",
                        "attribute_options": "Ja|Nei",
                        "default_value": "",
                        "is_conditional": 0,
                        "show_on_field": 0,
                        "show_on_value": "",
                        "default_task_notes": "",
                        "default_task_attachments": "",
                        "default_task_rule": "",
                        "sort_order": 1
                    },
                    {
                        "attribute_id":"",
                        "client_id":"",
                        "cf_master_id":"",
                        "cf_step_id":"",
                        "cf_block_id":"",
                        "label": "Kommentar",
                        "description": "",
                        "type": "textarea",
                        "is_mandetory": "0",
                        "attribute_options": "",
                        "default_value": "",
                        "is_conditional": 0,
                        "show_on_field": 0,
                        "show_on_value": "",
                        "default_task_notes": "",
                        "default_task_attachments": "",
                        "default_task_rule": "",
                        "sort_order": 2
                    },
                    {
                        "attribute_id":"",
                        "client_id":"",
                        "cf_master_id":"",
                        "cf_step_id":"",
                        "cf_block_id":"",
                        "label": "Oppgaver",
                        "description": "Hvis selskapet finnes i Brønnlysundregistrene henter vi aktuell informasjon og forhåndsutfyller for deg.",
                        "type": "freetext",
                        "is_mandetory": "0",
                        "attribute_options": "",
                        "default_value": "",
                        "is_conditional": 1,
                        "show_on_field": 0,
                        "show_on_value": "ja",
                        "default_task_notes": "",
                        "default_task_attachments": "",
                        "default_task_rule": "",
                        "sort_order": 3
                    },
                    {
                        "attribute_id":"",
                        "client_id":"",
                        "cf_master_id":"",
                        "cf_step_id":"",
                        "cf_block_id":"",
                        "label": "Sende periodisk rapport",
                        "description": "",
                        "type": "taskform",
                        "is_mandetory": "0",
                        "attribute_options": "",
                        "default_value": "",
                        "is_conditional": 1,
                        "show_on_field": 0,
                        "show_on_value": "ja",
                        "default_task_notes": "",
                        "default_task_attachments": "",
                        "default_task_rule": "",
                        "sort_order": 4
                    }
                ]
            }
        ]
    },
    {
        "step": 5,
        "step_id":"",
        "cf_master_id":"",
        "category_id":"",
        "sort_order": 5,
        "block_data": [
            {
                "block_id":"",
                "client_id":"",
                "cf_master_id":"",
                "cf_step_id":"",
                "category_id":"",
                "title": "Fakturering",
                "description": "Hvis selskapet finnes i Brønnlysundregistrene henter vi aktuell informasjon og forhåndsutfyller for deg.",
                "sort_order": 1,
                "attributes": [
                    {
                        "attribute_id":"",
                        "client_id":"",
                        "cf_master_id":"",
                        "cf_step_id":"",
                        "cf_block_id":"",
                        "label": "Får kunden merverdikompensasjon?",
                        "description": "",
                        "type": "boolean",
                        "is_mandetory": "0",
                        "attribute_options": "Ja|Nei",
                        "default_value": "",
                        "is_conditional": 0,
                        "show_on_field": 0,
                        "show_on_value": "",
                        "default_task_notes": "",
                        "default_task_attachments": "",
                        "default_task_rule": "",
                        "sort_order": 1
                    },
                    {
                        "attribute_id":"",
                        "client_id":"",
                        "cf_master_id":"",
                        "cf_step_id":"",
                        "cf_block_id":"",
                        "label": "Oppgaver",
                        "description": "Hvis selskapet finnes i Brønnlysundregistrene henter vi aktuell informasjon og forhåndsutfyller for deg.",
                        "type": "freetext",
                        "is_mandetory": "0",
                        "attribute_options": "",
                        "default_value": "",
                        "is_conditional": 1,
                        "show_on_field": 0,
                        "show_on_value": "ja",
                        "default_task_notes": "",
                        "default_task_attachments": "",
                        "default_task_rule": "",
                        "sort_order": 3
                    },
                    {
                        "attribute_id":"",
                        "client_id":"",
                        "cf_master_id":"",
                        "cf_step_id":"",
                        "cf_block_id":"",
                        "label": "Minne kunden på å sende fakturagrunnlag",
                        "description": "",
                        "type": "taskform",
                        "is_mandetory": "0",
                        "attribute_options": "",
                        "default_value": "",
                        "is_conditional": 1,
                        "show_on_field": 0,
                        "show_on_value": "ja",
                        "default_task_notes": "",
                        "default_task_attachments": "",
                        "default_task_rule": "",
                        "sort_order": 4
                    },
                    {
                        "attribute_id":"",
                        "client_id":"",
                        "cf_master_id":"",
                        "cf_step_id":"",
                        "cf_block_id":"",
                        "label": "Fakturere for kunden",
                        "description": "",
                        "type": "taskform",
                        "is_mandetory": "0",
                        "attribute_options": "",
                        "default_value": "",
                        "is_conditional": 1,
                        "show_on_field": 0,
                        "show_on_value": "ja",
                        "default_task_notes": "",
                        "default_task_attachments": "",
                        "default_task_rule": "",
                        "sort_order": 5
                    },
                    {
                        "attribute_id":"",
                        "client_id":"",
                        "cf_master_id":"",
                        "cf_step_id":"",
                        "cf_block_id":"",
                        "label": "Kommentar",
                        "description": "",
                        "type": "textarea",
                        "is_mandetory": "0",
                        "attribute_options": "",
                        "default_value": "",
                        "is_conditional": 0,
                        "show_on_field": 0,
                        "show_on_value": "",
                        "default_task_notes": "",
                        "default_task_attachments": "",
                        "default_task_rule": "",
                        "sort_order": 2
                    }
                ]
            },
            {
                "block_id":"",
                "client_id":"",
                "cf_master_id":"",
                "cf_step_id":"",
                "category_id":"",
                "title": "Purrerutiner",
                "description": "Hvis selskapet finnes i Brønnlysundregistrene henter vi aktuell informasjon og forhåndsutfyller for deg.",
                "sort_order": 2,
                "attributes": [
                    {
                        "attribute_id":"",
                        "client_id":"",
                        "cf_master_id":"",
                        "cf_step_id":"",
                        "cf_block_id":"",
                        "label": "Skal regnskapsbyrået medvirke i faktureringsrutinen?",
                        "description": "",
                        "type": "boolean",
                        "is_mandetory": "0",
                        "attribute_options": "Ja|Nei",
                        "default_value": "",
                        "is_conditional": 0,
                        "show_on_field": 0,
                        "show_on_value": "",
                        "default_task_notes": "",
                        "default_task_attachments": "",
                        "default_task_rule": "",
                        "sort_order": 1
                    }
                ]
            },
            {
                "block_id":"",
                "client_id":"",
                "cf_master_id":"",
                "cf_step_id":"",
                "category_id":"",
                "title": "Innkassorutiner",
                "description": "Hvis selskapet finnes i Brønnlysundregistrene henter vi aktuell informasjon og forhåndsutfyller for deg.",
                "sort_order": 3,
                "attributes": [
                    {
                        "attribute_id":"",
                        "client_id":"",
                        "cf_master_id":"",
                        "cf_step_id":"",
                        "cf_block_id":"",
                        "label": "Skal regnskapsbyrået medvirke i faktureringsrutinen?",
                        "description": "",
                        "type": "boolean",
                        "is_mandetory": "0",
                        "attribute_options": "Ja|Nei",
                        "default_value": "",
                        "is_conditional": 0,
                        "show_on_field": 0,
                        "show_on_value": "",
                        "default_task_notes": "",
                        "default_task_attachments": "",
                        "default_task_rule": "",
                        "sort_order": 1
                    }
                ]
            }
        ]
    },
    {
        "step": 6,
        "step_id":"",
        "cf_master_id":"",
        "category_id":"",
        "sort_order": 6,
        "block_data": [
            {
                "block_id":"",
                "client_id":"",
                "cf_master_id":"",
                "cf_step_id":"",
                "category_id":"",
                "title": "Betalingsrutinen",
                "description": "Hvis selskapet finnes i Brønnlysundregistrene henter vi aktuell informasjon og forhåndsutfyller for deg.",
                "sort_order": 1,
                "attributes": [
                    {
                        "attribute_id":"",
                        "client_id":"",
                        "cf_master_id":"",
                        "cf_step_id":"",
                        "cf_block_id":"",
                        "label": "Skal regnskapsbyrået medvirke i faktureringsrutinen?",
                        "description": "",
                        "type": "boolean",
                        "is_mandetory": "0",
                        "attribute_options": "Ja|Nei",
                        "default_value": "",
                        "is_conditional": 0,
                        "show_on_field": 0,
                        "show_on_value": "",
                        "default_task_notes": "",
                        "default_task_attachments": "",
                        "default_task_rule": "",
                        "sort_order": 1
                    },
                    {
                        "attribute_id":"",
                        "client_id":"",
                        "cf_master_id":"",
                        "cf_step_id":"",
                        "cf_block_id":"",
                        "label": "Kommentar",
                        "description": "",
                        "type": "textarea",
                        "is_mandetory": "0",
                        "attribute_options": "",
                        "default_value": "",
                        "is_conditional": 0,
                        "show_on_field": 0,
                        "show_on_value": "",
                        "default_task_notes": "",
                        "default_task_attachments": "",
                        "default_task_rule": "",
                        "sort_order": 2
                    }
                ]
            },
            {
                "block_id":"",
                "client_id":"",
                "cf_master_id":"",
                "cf_step_id":"",
                "category_id":"",
                "title": "MVA",
                "description": "Hvis selskapet finnes i Brønnlysundregistrene henter vi aktuell informasjon og forhåndsutfyller for deg.",
                "sort_order": 1,
                "attributes": [
                    {
                        "attribute_id":"",
                        "client_id":"",
                        "cf_master_id":"",
                        "cf_step_id":"",
                        "cf_block_id":"",
                        "label": "Skal regnskapbyrået betale MVA? ",
                        "description": "",
                        "type": "boolean",
                        "is_mandetory": "0",
                        "attribute_options": "Ja|Nei",
                        "default_value": "",
                        "is_conditional": 0,
                        "show_on_field": 0,
                        "show_on_value": "",
                        "default_task_notes": "",
                        "default_task_attachments": "",
                        "default_task_rule": "",
                        "sort_order": 1
                    },
                    {
                        "attribute_id":"",
                        "client_id":"",
                        "cf_master_id":"",
                        "cf_step_id":"",
                        "cf_block_id":"",
                        "label": "Oppgaver",
                        "description": "Hvis selskapet finnes i Brønnlysundregistrene henter vi aktuell informasjon og forhåndsutfyller for deg.",
                        "type": "freetext",
                        "is_mandetory": "0",
                        "attribute_options": "",
                        "default_value": "",
                        "is_conditional": 1,
                        "show_on_field": 0,
                        "show_on_value": "ja",
                        "default_task_notes": "",
                        "default_task_attachments": "",
                        "default_task_rule": "",
                        "sort_order": 2
                    },
                    {
                        "attribute_id":"",
                        "client_id":"",
                        "cf_master_id":"",
                        "cf_step_id":"",
                        "cf_block_id":"",
                        "label": "Betale MVA",
                        "description": "",
                        "type": "taskform",
                        "is_mandetory": "0",
                        "attribute_options": "",
                        "default_value": "",
                        "is_conditional": 1,
                        "show_on_field": 0,
                        "show_on_value": "ja",
                        "default_task_notes": "",
                        "default_task_attachments": "",
                        "default_task_rule": "",
                        "sort_order": 3
                    }
                ]
            },
            {
                "block_id":"",
                "client_id":"",
                "cf_master_id":"",
                "cf_step_id":"",
                "category_id":"",
                "title": "Leverandørfakturaer",
                "description": "Hvis selskapet finnes i Brønnlysundregistrene henter vi aktuell informasjon og forhåndsutfyller for deg.",
                "sort_order": 1,
                "attributes": [
                    {
                        "attribute_id":"",
                        "client_id":"",
                        "cf_master_id":"",
                        "cf_step_id":"",
                        "cf_block_id":"",
                        "label": "Skal regnskapbyrået betale leverandørfakturaer?",
                        "description": "",
                        "type": "boolean",
                        "is_mandetory": "0",
                        "attribute_options": "Ja|Nei",
                        "default_value": "",
                        "is_conditional": 0,
                        "show_on_field": 0,
                        "show_on_value": "",
                        "default_task_notes": "",
                        "default_task_attachments": "",
                        "default_task_rule": "",
                        "sort_order": 1
                    },
                    {
                        "attribute_id":"",
                        "client_id":"",
                        "cf_master_id":"",
                        "cf_step_id":"",
                        "cf_block_id":"",
                        "label": "Oppgaver",
                        "description": "Hvis selskapet finnes i Brønnlysundregistrene henter vi aktuell informasjon og forhåndsutfyller for deg.",
                        "type": "freetext",
                        "is_mandetory": "0",
                        "attribute_options": "",
                        "default_value": "",
                        "is_conditional": 1,
                        "show_on_field": 0,
                        "show_on_value": "ja",
                        "default_task_notes": "",
                        "default_task_attachments": "",
                        "default_task_rule": "",
                        "sort_order": 2
                    },
                    {
                        "attribute_id":"",
                        "client_id":"",
                        "cf_master_id":"",
                        "cf_step_id":"",
                        "cf_block_id":"",
                        "label": "Betale leverandørfakturaer",
                        "description": "",
                        "type": "taskform",
                        "is_mandetory": "0",
                        "attribute_options": "",
                        "default_value": "",
                        "is_conditional": 1,
                        "show_on_field": 0,
                        "show_on_value": "ja",
                        "default_task_notes": "",
                        "default_task_attachments": "",
                        "default_task_rule": "",
                        "sort_order": 3
                    }
                ]
            },
            {
                "block_id":"",
                "client_id":"",
                "cf_master_id":"",
                "cf_step_id":"",
                "category_id":"",
                "title": "Lønn",
                "description": "Hvis selskapet finnes i Brønnlysundregistrene henter vi aktuell informasjon og forhåndsutfyller for deg.",
                "sort_order": 1,
                "attributes": [
                    {
                        "attribute_id":"",
                        "client_id":"",
                        "cf_master_id":"",
                        "cf_step_id":"",
                        "cf_block_id":"",
                        "label": "Skal regnskapbyrået utbetale lønn?",
                        "description": "",
                        "type": "boolean",
                        "is_mandetory": "0",
                        "attribute_options": "Ja|Nei",
                        "default_value": "",
                        "is_conditional": 0,
                        "show_on_field": 0,
                        "show_on_value": "",
                        "default_task_notes": "",
                        "default_task_attachments": "",
                        "default_task_rule": "",
                        "sort_order": 1
                    },
                    {
                        "attribute_id":"",
                        "client_id":"",
                        "cf_master_id":"",
                        "cf_step_id":"",
                        "cf_block_id":"",
                        "label": "Oppgaver",
                        "description": "Hvis selskapet finnes i Brønnlysundregistrene henter vi aktuell informasjon og forhåndsutfyller for deg.",
                        "type": "freetext",
                        "is_mandetory": "0",
                        "attribute_options": "",
                        "default_value": "",
                        "is_conditional": 1,
                        "show_on_field": 0,
                        "show_on_value": "ja",
                        "default_task_notes": "",
                        "default_task_attachments": "",
                        "default_task_rule": "",
                        "sort_order": 2
                    },
                    {
                        "attribute_id":"",
                        "client_id":"",
                        "cf_master_id":"",
                        "cf_step_id":"",
                        "cf_block_id":"",
                        "label": "Utbetale lønn",
                        "description": "",
                        "type": "taskform",
                        "is_mandetory": "0",
                        "attribute_options": "",
                        "default_value": "",
                        "is_conditional": 1,
                        "show_on_field": 0,
                        "show_on_value": "ja",
                        "default_task_notes": "",
                        "default_task_attachments": "",
                        "default_task_rule": "",
                        "sort_order": 3
                    }
                ]
            },
            {
                "block_id":"",
                "client_id":"",
                "cf_master_id":"",
                "cf_step_id":"",
                "category_id":"",
                "title": "Arbeidsgiveravgift",
                "description": "Hvis selskapet finnes i Brønnlysundregistrene henter vi aktuell informasjon og forhåndsutfyller for deg.",
                "sort_order": 1,
                "attributes": [
                    {
                        "attribute_id":"",
                        "client_id":"",
                        "cf_master_id":"",
                        "cf_step_id":"",
                        "cf_block_id":"",
                        "label": "Skal regnskapbyrået betale AGA?? ",
                        "description": "",
                        "type": "boolean",
                        "is_mandetory": "0",
                        "attribute_options": "Ja|Nei",
                        "default_value": "",
                        "is_conditional": 0,
                        "show_on_field": 0,
                        "show_on_value": "",
                        "default_task_notes": "",
                        "default_task_attachments": "",
                        "default_task_rule": "",
                        "sort_order": 1
                    },
                    {
                        "attribute_id":"",
                        "client_id":"",
                        "cf_master_id":"",
                        "cf_step_id":"",
                        "cf_block_id":"",
                        "label": "Oppgaver",
                        "description": "Hvis selskapet finnes i Brønnlysundregistrene henter vi aktuell informasjon og forhåndsutfyller for deg.",
                        "type": "freetext",
                        "is_mandetory": "0",
                        "attribute_options": "",
                        "default_value": "",
                        "is_conditional": 1,
                        "show_on_field": 0,
                        "show_on_value": "ja",
                        "default_task_notes": "",
                        "default_task_attachments": "",
                        "default_task_rule": "",
                        "sort_order": 2
                    },
                    {
                        "attribute_id":"",
                        "client_id":"",
                        "cf_master_id":"",
                        "cf_step_id":"",
                        "cf_block_id":"",
                        "label": "Betale AGA",
                        "description": "",
                        "type": "taskform",
                        "is_mandetory": "0",
                        "attribute_options": "",
                        "default_value": "",
                        "is_conditional": 1,
                        "show_on_field": 0,
                        "show_on_value": "ja",
                        "default_task_notes": "",
                        "default_task_attachments": "",
                        "default_task_rule": "",
                        "sort_order": 3
                    }
                ]
            }
        ]
    },
    {
        "step": 7,
        "step_id":"",
        "cf_master_id":"",
        "category_id":"",
        "sort_order": 7,
        "block_data": [
            {
                "block_id":"",
                "client_id":"",
                "cf_master_id":"",
                "cf_step_id":"",
                "category_id":"",
                "title": "Lønnsrutinen",
                "description": "Hvis selskapet finnes i Brønnlysundregistrene henter vi aktuell informasjon og forhåndsutfyller for deg.",
                "sort_order": 1,
                "attributes": [
                    {
                        "attribute_id":"",
                        "client_id":"",
                        "cf_master_id":"",
                        "cf_step_id":"",
                        "cf_block_id":"",
                        "label": "Skal regnskapsbyrået medvirke i lønnsrutinen?",
                        "description": "",
                        "type": "boolean",
                        "is_mandetory": "0",
                        "attribute_options": "Ja|Nei",
                        "default_value": "",
                        "is_conditional": 0,
                        "show_on_field": 0,
                        "show_on_value": "",
                        "default_task_notes": "",
                        "default_task_attachments": "",
                        "default_task_rule": "",
                        "sort_order": 1
                    },
                    {
                        "attribute_id":"",
                        "client_id":"",
                        "cf_master_id":"",
                        "cf_step_id":"",
                        "cf_block_id":"",
                        "label": "Kommentar",
                        "description": "",
                        "type": "textarea",
                        "is_mandetory": "0",
                        "attribute_options": "",
                        "default_value": "",
                        "is_conditional": 0,
                        "show_on_field": 0,
                        "show_on_value": "",
                        "default_task_notes": "",
                        "default_task_attachments": "",
                        "default_task_rule": "",
                        "sort_order": 2
                    },
                    {
                        "attribute_id":"",
                        "client_id":"",
                        "cf_master_id":"",
                        "cf_step_id":"",
                        "cf_block_id":"",
                        "label": "Når har kunden lønnsutbetaling? ",
                        "description": "",
                        "type": "selectbox",
                        "is_mandetory": "0",
                        "attribute_options": "på forespørsel|fast dato",
                        "default_value": "",
                        "is_conditional": 1,
                        "show_on_field": 0,
                        "show_on_value": "ja",
                        "default_task_notes": "",
                        "default_task_attachments": "",
                        "default_task_rule": "",
                        "sort_order": 3
                    },
                    {
                        "attribute_id":"",
                        "client_id":"",
                        "cf_master_id":"",
                        "cf_step_id":"",
                        "cf_block_id":"",
                        "label": "Oppgaver",
                        "description": "Hvis selskapet finnes i Brønnlysundregistrene henter vi aktuell informasjon og forhåndsutfyller for deg.",
                        "type": "freetext",
                        "is_mandetory": "0",
                        "attribute_options": "",
                        "default_value": "",
                        "is_conditional": 1,
                        "show_on_field": 0,
                        "show_on_value": "fast dato",
                        "default_task_notes": "",
                        "default_task_attachments": "",
                        "default_task_rule": "",
                        "sort_order": 4
                    },
                    {
                        "attribute_id":"",
                        "client_id":"",
                        "cf_master_id":"",
                        "cf_step_id":"",
                        "cf_block_id":"",
                        "label": "Minne kunden på å sende lønnsgrunnlag",
                        "description": "",
                        "type": "taskform",
                        "is_mandetory": "0",
                        "attribute_options": "",
                        "default_value": "",
                        "is_conditional": 1,
                        "show_on_field": 0,
                        "show_on_value": "fast dato",
                        "default_task_notes": "",
                        "default_task_attachments": "",
                        "default_task_rule": "",
                        "sort_order": 5
                    },
                    {
                        "attribute_id":"",
                        "client_id":"",
                        "cf_master_id":"",
                        "cf_step_id":"",
                        "cf_block_id":"",
                        "label": "Utarbeide og bokføre lønnsgrunnlag",
                        "description": "",
                        "type": "taskform",
                        "is_mandetory": "0",
                        "attribute_options": "",
                        "default_value": "",
                        "is_conditional": 1,
                        "show_on_field": 0,
                        "show_on_value": "fast dato",
                        "default_task_notes": "",
                        "default_task_attachments": "",
                        "default_task_rule": "",
                        "sort_order": 6
                    }
                ]
            },
            {
                "block_id":"",
                "client_id":"",
                "cf_master_id":"",
                "cf_step_id":"",
                "category_id":"",
                "title": "Oppgaver",
                "description": "Hvis selskapet finnes i Brønnlysundregistrene henter vi aktuell informasjon og forhåndsutfyller for deg.",
                "sort_order": 1,
                "attributes": [
                    {
                        "attribute_id":"",
                        "client_id":"",
                        "cf_master_id":"",
                        "cf_step_id":"",
                        "cf_block_id":"",
                        "label": "Avstemme skatt og arbeidsgiveravgift",
                        "description": "",
                        "type": "taskform",
                        "is_mandetory": "0",
                        "attribute_options": "",
                        "default_value": "",
                        "is_conditional": 0,
                        "show_on_field": 0,
                        "show_on_value": "",
                        "default_task_notes": "",
                        "default_task_attachments": "",
                        "default_task_rule": "",
                        "sort_order": 1
                    },
                    {
                        "attribute_id":"",
                        "client_id":"",
                        "cf_master_id":"",
                        "cf_step_id":"",
                        "cf_block_id":"",
                        "label": "Innrapportere arbeidsforhold (a-melding)",
                        "description": "",
                        "type": "taskform",
                        "is_mandetory": "0",
                        "attribute_options": "",
                        "default_value": "",
                        "is_conditional": 0,
                        "show_on_field": 0,
                        "show_on_value": "",
                        "default_task_notes": "",
                        "default_task_attachments": "",
                        "default_task_rule": "",
                        "sort_order": 2
                    },
                    {
                        "attribute_id":"",
                        "client_id":"",
                        "cf_master_id":"",
                        "cf_step_id":"",
                        "cf_block_id":"",
                        "label": "Lønnsrapport til Kunden",
                        "description": "",
                        "type": "taskform",
                        "is_mandetory": "0",
                        "attribute_options": "",
                        "default_value": "",
                        "is_conditional": 0,
                        "show_on_field": 0,
                        "show_on_value": "",
                        "default_task_notes": "",
                        "default_task_attachments": "",
                        "default_task_rule": "",
                        "sort_order": 3
                    },
                    {
                        "attribute_id":"",
                        "client_id":"",
                        "cf_master_id":"",
                        "cf_step_id":"",
                        "cf_block_id":"",
                        "label": "Sende NAV krav om refusjon av sykepenger ",
                        "description": "",
                        "type": "taskform",
                        "is_mandetory": "0",
                        "attribute_options": "",
                        "default_value": "",
                        "is_conditional": 0,
                        "show_on_field": 0,
                        "show_on_value": "",
                        "default_task_notes": "",
                        "default_task_attachments": "",
                        "default_task_rule": "",
                        "sort_order": 4
                    },
                    {
                        "attribute_id":"",
                        "client_id":"",
                        "cf_master_id":"",
                        "cf_step_id":"",
                        "cf_block_id":"",
                        "label": "Sende NAV krav om andre lønnsrelaterte refusjoner",
                        "description": "",
                        "type": "taskform",
                        "is_mandetory": "0",
                        "attribute_options": "",
                        "default_value": "",
                        "is_conditional": 0,
                        "show_on_field": 0,
                        "show_on_value": "",
                        "default_task_notes": "",
                        "default_task_attachments": "",
                        "default_task_rule": "",
                        "sort_order": 5
                    },
                    {
                        "attribute_id":"",
                        "client_id":"",
                        "cf_master_id":"",
                        "cf_step_id":"",
                        "cf_block_id":"",
                        "label": "Kontroll refusjoner mottatt fra NAV",
                        "description": "",
                        "type": "taskform",
                        "is_mandetory": "0",
                        "attribute_options": "",
                        "default_value": "",
                        "is_conditional": 0,
                        "show_on_field": 0,
                        "show_on_value": "",
                        "default_task_notes": "",
                        "default_task_attachments": "",
                        "default_task_rule": "",
                        "sort_order": 6
                    },
                    {
                        "attribute_id":"",
                        "client_id":"",
                        "cf_master_id":"",
                        "cf_step_id":"",
                        "cf_block_id":"",
                        "label": "Sammenstillingsoppgave til arbeidstakere",
                        "description": "",
                        "type": "taskform",
                        "is_mandetory": "0",
                        "attribute_options": "",
                        "default_value": "",
                        "is_conditional": 0,
                        "show_on_field": 0,
                        "show_on_value": "",
                        "default_task_notes": "",
                        "default_task_attachments": "",
                        "default_task_rule": "",
                        "sort_order": 7
                    },
                    {
                        "attribute_id":"",
                        "client_id":"",
                        "cf_master_id":"",
                        "cf_step_id":"",
                        "cf_block_id":"",
                        "label": "Administrere forsikring",
                        "description": "",
                        "type": "taskform",
                        "is_mandetory": "0",
                        "attribute_options": "",
                        "default_value": "",
                        "is_conditional": 0,
                        "show_on_field": 0,
                        "show_on_value": "",
                        "default_task_notes": "",
                        "default_task_attachments": "",
                        "default_task_rule": "",
                        "sort_order": 8
                    },
                    {
                        "attribute_id":"",
                        "client_id":"",
                        "cf_master_id":"",
                        "cf_step_id":"",
                        "cf_block_id":"",
                        "label": "Administrere OTP/pensjonsordning",
                        "description": "",
                        "type": "taskform",
                        "is_mandetory": "0",
                        "attribute_options": "",
                        "default_value": "",
                        "is_conditional": 0,
                        "show_on_field": 0,
                        "show_on_value": "",
                        "default_task_notes": "",
                        "default_task_attachments": "",
                        "default_task_rule": "",
                        "sort_order": 9
                    }
                ]
            }
        ]
    },
    {
        "step": 8,
        "step_id":"",
        "cf_master_id":"",
        "category_id":"",
        "sort_order": 8,
        "block_data": [
            {
                "block_id":"",
                "client_id":"",
                "cf_master_id":"",
                "cf_step_id":"",
                "category_id":"",
                "title": "Årsoppgjørsrutinen",
                "description": "Hvis selskapet finnes i Brønnlysundregistrene henter vi aktuell informasjon og forhåndsutfyller for deg.",
                "sort_order": 1,
                "attributes": [
                    {
                        "attribute_id":"",
                        "client_id":"",
                        "cf_master_id":"",
                        "cf_step_id":"",
                        "cf_block_id":"",
                        "label": "Skal regnskapsbyrået medvirke i årsoppgjørsrutinen?",
                        "description": "",
                        "type": "boolean",
                        "is_mandetory": "0",
                        "attribute_options": "Ja|Nei",
                        "default_value": "",
                        "is_conditional": 0,
                        "show_on_field": 0,
                        "show_on_value": "",
                        "default_task_notes": "",
                        "default_task_attachments": "",
                        "default_task_rule": "",
                        "sort_order": 1
                    },
                    {
                        "attribute_id":"",
                        "client_id":"",
                        "cf_master_id":"",
                        "cf_step_id":"",
                        "cf_block_id":"",
                        "label": "Oppgaver",
                        "description": "Hvis selskapet finnes i Brønnlysundregistrene henter vi aktuell informasjon og forhåndsutfyller for deg.",
                        "type": "freetext",
                        "is_mandetory": "0",
                        "attribute_options": "",
                        "default_value": "",
                        "is_conditional": 1,
                        "show_on_field": 0,
                        "show_on_value": "ja",
                        "default_task_notes": "",
                        "default_task_attachments": "",
                        "default_task_rule": "",
                        "sort_order": 2
                    },
                    {
                        "attribute_id":"",
                        "client_id":"",
                        "cf_master_id":"",
                        "cf_step_id":"",
                        "cf_block_id":"",
                        "label": "A-reg oppgave",
                        "description": "",
                        "type": "taskform",
                        "is_mandetory": "0",
                        "attribute_options": "",
                        "default_value": "",
                        "is_conditional": 1,
                        "show_on_field": 0,
                        "show_on_value": "ja",
                        "default_task_notes": "",
                        "default_task_attachments": "",
                        "default_task_rule": "",
                        "sort_order": 3
                    },
                    {
                        "attribute_id":"",
                        "client_id":"",
                        "cf_master_id":"",
                        "cf_step_id":"",
                        "cf_block_id":"",
                        "label": "Levere skattemelding",
                        "description": "",
                        "type": "taskform",
                        "is_mandetory": "0",
                        "attribute_options": "",
                        "default_value": "",
                        "is_conditional": 1,
                        "show_on_field": 0,
                        "show_on_value": "ja",
                        "default_task_notes": "",
                        "default_task_attachments": "",
                        "default_task_rule": "",
                        "sort_order": 4
                    },
                    {
                        "attribute_id":"",
                        "client_id":"",
                        "cf_master_id":"",
                        "cf_step_id":"",
                        "cf_block_id":"",
                        "label": "Sende inn offentlig regnskap",
                        "description": "",
                        "type": "taskform",
                        "is_mandetory": "0",
                        "attribute_options": "",
                        "default_value": "",
                        "is_conditional": 1,
                        "show_on_field": 0,
                        "show_on_value": "ja",
                        "default_task_notes": "",
                        "default_task_attachments": "",
                        "default_task_rule": "",
                        "sort_order": 5
                    },
                    {
                        "attribute_id":"",
                        "client_id":"",
                        "cf_master_id":"",
                        "cf_step_id":"",
                        "cf_block_id":"",
                        "label": "Kommentar",
                        "description": "",
                        "type": "textarea",
                        "is_mandetory": "0",
                        "attribute_options": "",
                        "default_value": "",
                        "is_conditional": 0,
                        "show_on_field": 0,
                        "show_on_value": "",
                        "default_task_notes": "",
                        "default_task_attachments": "",
                        "default_task_rule": "",
                        "sort_order": 2
                    }
                ]
            }
        ]
    },
    {
        "step": 9,
        "step_id":"",
        "cf_master_id":"",
        "category_id":"",
        "sort_order": 9,
        "block_data": [
            {
                "block_id":"",
                "client_id":"",
                "cf_master_id":"",
                "cf_step_id":"",
                "category_id":"",
                "title": "Annet",
                "description": "Hvis selskapet finnes i Brønnlysundregistrene henter vi aktuell informasjon og forhåndsutfyller for deg.",
                "sort_order": 1,
                "attributes": [
                    {
                        "attribute_id":"",
                        "client_id":"",
                        "cf_master_id":"",
                        "cf_step_id":"",
                        "cf_block_id":"",
                        "label": "Kommentar",
                        "description": "",
                        "type": "textarea",
                        "is_mandetory": "0",
                        "attribute_options": "",
                        "default_value": "",
                        "is_conditional": 0,
                        "show_on_field": 0,
                        "show_on_value": "",
                        "default_task_notes": "",
                        "default_task_attachments": "",
                        "default_task_rule": "",
                        "sort_order": 1
                    }
                ]
            },
            {
                "block_id":"",
                "client_id":"",
                "cf_master_id":"",
                "cf_step_id":"",
                "category_id":"",
                "title": "Årsoppgjørsrutinen",
                "description": "Hvis selskapet finnes i Brønnlysundregistrene henter vi aktuell informasjon og forhåndsutfyller for deg.",
                "sort_order": 1,
                "attributes": [
                    {
                        "attribute_id":"",
                        "client_id":"",
                        "cf_master_id":"",
                        "cf_step_id":"",
                        "cf_block_id":"",
                        "label": "Skal regnskapsbyrået levere aksjonærregisteroppgave? ",
                        "description": "",
                        "type": "boolean",
                        "is_mandetory": "0",
                        "attribute_options": "Ja|Nei",
                        "default_value": "",
                        "is_conditional": 0,
                        "show_on_field": 0,
                        "show_on_value": "",
                        "default_task_notes": "",
                        "default_task_attachments": "",
                        "default_task_rule": "",
                        "sort_order": 3
                    },
                    {
                        "attribute_id":"",
                        "client_id":"",
                        "cf_master_id":"",
                        "cf_step_id":"",
                        "cf_block_id":"",
                        "label": "Oppgaver",
                        "description": "Hvis selskapet finnes i Brønnlysundregistrene henter vi aktuell informasjon og forhåndsutfyller for deg.",
                        "type": "freetext",
                        "is_mandetory": "0",
                        "attribute_options": "",
                        "default_value": "",
                        "is_conditional": 1,
                        "show_on_field": 0,
                        "show_on_value": "ja",
                        "default_task_notes": "",
                        "default_task_attachments": "",
                        "default_task_rule": "",
                        "sort_order": 4
                    },
                    {
                        "attribute_id":"",
                        "client_id":"",
                        "cf_master_id":"",
                        "cf_step_id":"",
                        "cf_block_id":"",
                        "label": "Innhente oppdatert aksjeeierbok ",
                        "description": "",
                        "type": "taskform",
                        "is_mandetory": "0",
                        "attribute_options": "",
                        "default_value": "",
                        "is_conditional": 1,
                        "show_on_field": 0,
                        "show_on_value": "ja",
                        "default_task_notes": "",
                        "default_task_attachments": "",
                        "default_task_rule": "",
                        "sort_order": 5
                    },
                    {
                        "attribute_id":"",
                        "client_id":"",
                        "cf_master_id":"",
                        "cf_step_id":"",
                        "cf_block_id":"",
                        "label": "Levere aksjonærregisteroppgave ",
                        "description": "",
                        "type": "taskform",
                        "is_mandetory": "0",
                        "attribute_options": "",
                        "default_value": "",
                        "is_conditional": 1,
                        "show_on_field": 0,
                        "show_on_value": "ja",
                        "default_task_notes": "",
                        "default_task_attachments": "",
                        "default_task_rule": "",
                        "sort_order": 6
                    },
                    {
                        "attribute_id":"",
                        "client_id":"",
                        "cf_master_id":"",
                        "cf_step_id":"",
                        "cf_block_id":"",
                        "label": "Kommentar",
                        "description": "",
                        "type": "textarea",
                        "is_mandetory": "0",
                        "attribute_options": "",
                        "default_value": "",
                        "is_conditional": 1,
                        "show_on_field": 0,
                        "show_on_value": "ja",
                        "default_task_notes": "",
                        "default_task_attachments": "",
                        "default_task_rule": "",
                        "sort_order": 7
                    }
                ]
            }
        ]
    }
]